{
  "listItems":[
    {
      "title":"为什么我下不了单？",
      "description":"一人限购一张，如您之前已经下单并且付款成功，将无法再次下单。除此之外如有异常，请联系客服。"
    },
    {
      "title":"购买了什么时候能到货？",
      "description":"快递默认发顺丰，时间1-2天，如部分非顺丰配送范围地区，则改发EMS快递，时间3-5天。"
    },
    {
      "title":"套餐什么时候开通？",
      "description":"您的证照上传并审核成功后，两个工作日内为您开通。"
    },
    {
      "title":"我每个月需要交多少钱月租？",
      "description":"套餐月租-当月返还的金额=每月实交月租<br><em>（例：204套餐，每月为您减免102元，您每月需缴费102元）</em>"
    },
    {
      "title":"一个人可以购买多张卡吗？",
      "description":"每个身份证限购一张，如已有注销、开通记录不可再次办理"
    },
    {
      "title":"套餐的月租是一直5折收费吗？",
      "description":"并不是，优惠期限为3年，3年后恢复原价。"
    },
    {
      "title":"可以选择其他地区的号码吗？",
      "description":"号码归属地仅限广东，套餐全国无漫游，哪里用都一样。"
    },
    {
      "title":"不想用了可以退换吗？",
      "description":"手机卡属于实名制特殊产品，开户并使用后，无法进行二次销售，如使用途中不想用了，可联系客服为您注销套餐，请谅解。"
    },
    {
      "title":"到货后，没激活可以退货吗？",
      "description":"可以，若因个人问题导致的退货（电信黑名单、证照不符合、不想要），需用户承担快递费。"
    }
  ],
  "listTips":"123"
}